setup.py
nombre_normalizer/__init__.py
nombre_normalizer/cli.py
nombre_normalizer/nombre_normalizer.py
nombre_normalizer.egg-info/PKG-INFO
nombre_normalizer.egg-info/SOURCES.txt
nombre_normalizer.egg-info/dependency_links.txt
nombre_normalizer.egg-info/entry_points.txt
nombre_normalizer.egg-info/requires.txt
nombre_normalizer.egg-info/top_level.txt
tests/test_normalizer.py